django_query_analyzer/__init__.py
django_query_analyzer/admin.py
django_query_analyzer/apps.py
django_query_analyzer/middleware.py
django_query_analyzer/models.py
django_query_analyzer/signals.py
django_query_analyzer/tests.py
django_query_analyzer/urls.py
django_query_analyzer/views.py
django_query_analyzer/migrations/0001_initial.py
django_query_analyzer/migrations/__init__.py
django_query_analyzer/templates/django_query_analyzer/django_query_analyzer.html
django_query_analyzer-0.0.17.dist-info/LICENSE
django_query_analyzer-0.0.17.dist-info/METADATA
django_query_analyzer-0.0.17.dist-info/WHEEL
django_query_analyzer-0.0.17.dist-info/top_level.txt
django_query_analyzer-0.0.17.dist-info/RECORD
