Metadata-Version: 2.1
Name: django-query-analyzer
Version: 0.0.17
Summary: Python package for query analysis and monitoring in Django
Author: Muhammed Shaheen
Author-email: muhammedshaheen.tkb@gmail.com
License: MIT
Keywords: python,django,query,sql-query,query-analyzer,query-monitoring,query-analysis,django-query-analyzer,django-query-monitoring,django-query-analysis
License-File: LICENSE
Requires-Dist: Django
